aedev/setup_project.py
aedev_setup_project-0.3.23.dist-info/licenses/LICENSE.md
aedev_setup_project-0.3.23.dist-info/METADATA
aedev_setup_project-0.3.23.dist-info/WHEEL
aedev_setup_project-0.3.23.dist-info/top_level.txt
aedev_setup_project-0.3.23.dist-info/zip-safe
aedev_setup_project-0.3.23.dist-info/RECORD
